LICENSE
README.md
setup.py
paper2vec/__main__.py
paper2vec/abc.py
paper2vec/config.py
paper2vec.egg-info/PKG-INFO
paper2vec.egg-info/SOURCES.txt
paper2vec.egg-info/dependency_links.txt
paper2vec.egg-info/requires.txt
paper2vec.egg-info/top_level.txt
paper2vec/datadestination/__init__.py
paper2vec/datadestination/qdrant.py
paper2vec/datasource/__init__.py
paper2vec/datasource/neo4j.py
paper2vec/retrieverdestination/__init__.py
paper2vec/retrieverdestination/openai/retrieval_plugin.py
paper2vec/retrieverdestination/openai/fast_api_client/__init__.py
paper2vec/retrieverdestination/openai/fast_api_client/client.py
paper2vec/retrieverdestination/openai/fast_api_client/errors.py
paper2vec/retrieverdestination/openai/fast_api_client/types.py
paper2vec/retrieverdestination/openai/fast_api_client/api/__init__.py
paper2vec/retrieverdestination/openai/fast_api_client/api/default/__init__.py
paper2vec/retrieverdestination/openai/fast_api_client/api/default/delete_delete_delete.py
paper2vec/retrieverdestination/openai/fast_api_client/api/default/query_main_query_post.py
paper2vec/retrieverdestination/openai/fast_api_client/api/default/upsert_file_upsert_file_post.py
paper2vec/retrieverdestination/openai/fast_api_client/api/default/upsert_upsert_post.py
paper2vec/retrieverdestination/openai/fast_api_client/models/__init__.py
paper2vec/retrieverdestination/openai/fast_api_client/models/body_upsert_file_upsert_file_post.py
paper2vec/retrieverdestination/openai/fast_api_client/models/delete_request.py
paper2vec/retrieverdestination/openai/fast_api_client/models/delete_response.py
paper2vec/retrieverdestination/openai/fast_api_client/models/document.py
paper2vec/retrieverdestination/openai/fast_api_client/models/document_chunk_metadata.py
paper2vec/retrieverdestination/openai/fast_api_client/models/document_chunk_with_score.py
paper2vec/retrieverdestination/openai/fast_api_client/models/document_metadata.py
paper2vec/retrieverdestination/openai/fast_api_client/models/document_metadata_filter.py
paper2vec/retrieverdestination/openai/fast_api_client/models/http_validation_error.py
