Metadata-Version: 2.1
Name: paper2vec
Version: 1.1
Summary: Turn your collected papers into vectors!
Home-page: https://github.com/yindaheng98/paper2vec
Author: yindaheng98
Author-email: yindaheng98@gmail.com
Classifier: Programming Language :: Python :: 3
Classifier: License :: OSI Approved :: MIT License
Classifier: Operating System :: OS Independent
License-File: LICENSE
